{
  "_meta": {
    "language": "zh-Hans",
    "version": "1.1.0",
    "total": 210,
    "categories": ["Animals", "Food", "Places", "Actions", "Objects", "People", "Nature"]
  },
  "words": [
    { "id": "zh_001", "text": "大熊猫", "category": "Animals", "difficulty": "easy" },
    { "id": "zh_002", "text": "金鱼", "category": "Animals", "difficulty": "easy" },
    { "id": "zh_003", "text": "老虎", "category": "Animals", "difficulty": "easy" },
    { "id": "zh_004", "text": "企鹅", "category": "Animals", "difficulty": "easy" },
    { "id": "zh_005", "text": "蝴蝶", "category": "Animals", "difficulty": "easy" },
    { "id": "zh_006", "text": "骆驼", "category": "Animals", "difficulty": "easy" },
    { "id": "zh_007", "text": "孔雀", "category": "Animals", "difficulty": "easy" },
    { "id": "zh_008", "text": "海豚", "category": "Animals", "difficulty": "easy" },
    { "id": "zh_009", "text": "变色龙", "category": "Animals", "difficulty": "medium" },
    { "id": "zh_010", "text": "穿山甲", "category": "Animals", "difficulty": "medium" },
    { "id": "zh_011", "text": "雪豹", "category": "Animals", "difficulty": "medium" },
    { "id": "zh_012", "text": "麋鹿", "category": "Animals", "difficulty": "medium" },
    { "id": "zh_013", "text": "儒艮", "category": "Animals", "difficulty": "hard" },
    { "id": "zh_014", "text": "白鳍豚", "category": "Animals", "difficulty": "hard" },
    { "id": "zh_015", "text": "扬子鳄", "category": "Animals", "difficulty": "hard" },
    { "id": "zh_016", "text": "朱鹮", "category": "Animals", "difficulty": "hard" },
    { "id": "zh_017", "text": "丹顶鹤", "category": "Animals", "difficulty": "medium" },
    { "id": "zh_018", "text": "藏羚羊", "category": "Animals", "difficulty": "medium" },
    { "id": "zh_019", "text": "金丝猴", "category": "Animals", "difficulty": "medium" },
    { "id": "zh_020", "text": "大闸蟹", "category": "Animals", "difficulty": "easy" },
    { "id": "zh_021", "text": "锦鲤", "category": "Animals", "difficulty": "easy" },
    { "id": "zh_022", "text": "蜈蚣", "category": "Animals", "difficulty": "easy" },
    { "id": "zh_023", "text": "壁虎", "category": "Animals", "difficulty": "easy" },
    { "id": "zh_024", "text": "飞蛾", "category": "Animals", "difficulty": "easy" },
    { "id": "zh_025", "text": "河豚", "category": "Animals", "difficulty": "easy" },
    { "id": "zh_026", "text": "黑熊", "category": "Animals", "difficulty": "easy" },
    { "id": "zh_027", "text": "猎豹", "category": "Animals", "difficulty": "easy" },
    { "id": "zh_028", "text": "刺猬", "category": "Animals", "difficulty": "easy" },
    { "id": "zh_029", "text": "章鱼", "category": "Animals", "difficulty": "easy" },
    { "id": "zh_030", "text": "海龟", "category": "Animals", "difficulty": "easy" },

    { "id": "zh_031", "text": "饺子", "category": "Food", "difficulty": "easy" },
    { "id": "zh_032", "text": "火锅", "category": "Food", "difficulty": "easy" },
    { "id": "zh_033", "text": "包子", "category": "Food", "difficulty": "easy" },
    { "id": "zh_034", "text": "月饼", "category": "Food", "difficulty": "easy" },
    { "id": "zh_035", "text": "汤圆", "category": "Food", "difficulty": "easy" },
    { "id": "zh_036", "text": "北京烤鸭", "category": "Food", "difficulty": "easy" },
    { "id": "zh_037", "text": "小笼包", "category": "Food", "difficulty": "medium" },
    { "id": "zh_038", "text": "糖葫芦", "category": "Food", "difficulty": "medium" },
    { "id": "zh_039", "text": "臭豆腐", "category": "Food", "difficulty": "medium" },
    { "id": "zh_040", "text": "佛跳墙", "category": "Food", "difficulty": "hard" },
    { "id": "zh_041", "text": "东坡肉", "category": "Food", "difficulty": "hard" },
    { "id": "zh_042", "text": "夫妻肺片", "category": "Food", "difficulty": "hard" },
    { "id": "zh_043", "text": "叫花鸡", "category": "Food", "difficulty": "medium" },
    { "id": "zh_044", "text": "红烧肉", "category": "Food", "difficulty": "medium" },
    { "id": "zh_045", "text": "凉皮", "category": "Food", "difficulty": "easy" },
    { "id": "zh_046", "text": "麻辣烫", "category": "Food", "difficulty": "easy" },
    { "id": "zh_047", "text": "宫保鸡丁", "category": "Food", "difficulty": "medium" },
    { "id": "zh_048", "text": "鱼香肉丝", "category": "Food", "difficulty": "medium" },
    { "id": "zh_049", "text": "回锅肉", "category": "Food", "difficulty": "medium" },
    { "id": "zh_050", "text": "麻婆豆腐", "category": "Food", "difficulty": "medium" },
    { "id": "zh_051", "text": "扬州炒饭", "category": "Food", "difficulty": "easy" },
    { "id": "zh_052", "text": "狮子头", "category": "Food", "difficulty": "hard" },
    { "id": "zh_053", "text": "锅贴", "category": "Food", "difficulty": "easy" },
    { "id": "zh_054", "text": "叉烧", "category": "Food", "difficulty": "easy" },
    { "id": "zh_055", "text": "豆花", "category": "Food", "difficulty": "easy" },
    { "id": "zh_056", "text": "年糕", "category": "Food", "difficulty": "easy" },
    { "id": "zh_057", "text": "粽子", "category": "Food", "difficulty": "easy" },
    { "id": "zh_058", "text": "皮蛋", "category": "Food", "difficulty": "medium" },
    { "id": "zh_059", "text": "螺蛳粉", "category": "Food", "difficulty": "hard" },
    { "id": "zh_060", "text": "蛋挞", "category": "Food", "difficulty": "easy" },

    { "id": "zh_061", "text": "长城", "category": "Places", "difficulty": "easy" },
    { "id": "zh_062", "text": "故宫", "category": "Places", "difficulty": "easy" },
    { "id": "zh_063", "text": "西藏", "category": "Places", "difficulty": "easy" },
    { "id": "zh_064", "text": "黄山", "category": "Places", "difficulty": "easy" },
    { "id": "zh_065", "text": "桂林", "category": "Places", "difficulty": "easy" },
    { "id": "zh_066", "text": "敦煌", "category": "Places", "difficulty": "medium" },
    { "id": "zh_067", "text": "乌镇", "category": "Places", "difficulty": "medium" },
    { "id": "zh_068", "text": "九寨沟", "category": "Places", "difficulty": "medium" },
    { "id": "zh_069", "text": "张家界", "category": "Places", "difficulty": "medium" },
    { "id": "zh_070", "text": "布达拉宫", "category": "Places", "difficulty": "hard" },
    { "id": "zh_071", "text": "莫高窟", "category": "Places", "difficulty": "hard" },
    { "id": "zh_072", "text": "西湖", "category": "Places", "difficulty": "easy" },
    { "id": "zh_073", "text": "天安门", "category": "Places", "difficulty": "easy" },
    { "id": "zh_074", "text": "丽江古城", "category": "Places", "difficulty": "medium" },
    { "id": "zh_075", "text": "三峡", "category": "Places", "difficulty": "medium" },
    { "id": "zh_076", "text": "泰山", "category": "Places", "difficulty": "easy" },
    { "id": "zh_077", "text": "兵马俑", "category": "Places", "difficulty": "medium" },
    { "id": "zh_078", "text": "颐和园", "category": "Places", "difficulty": "medium" },
    { "id": "zh_079", "text": "少林寺", "category": "Places", "difficulty": "medium" },
    { "id": "zh_080", "text": "峨眉山", "category": "Places", "difficulty": "medium" },
    { "id": "zh_081", "text": "西双版纳", "category": "Places", "difficulty": "hard" },
    { "id": "zh_082", "text": "鼓浪屿", "category": "Places", "difficulty": "hard" },
    { "id": "zh_083", "text": "大理古城", "category": "Places", "difficulty": "medium" },
    { "id": "zh_084", "text": "阳朔", "category": "Places", "difficulty": "hard" },
    { "id": "zh_085", "text": "凤凰古城", "category": "Places", "difficulty": "hard" },
    { "id": "zh_086", "text": "洱海", "category": "Places", "difficulty": "medium" },
    { "id": "zh_087", "text": "天池", "category": "Places", "difficulty": "medium" },
    { "id": "zh_088", "text": "东方明珠", "category": "Places", "difficulty": "easy" },
    { "id": "zh_089", "text": "黄浦江", "category": "Places", "difficulty": "medium" },
    { "id": "zh_090", "text": "珠穆朗玛峰", "category": "Places", "difficulty": "hard" },

    { "id": "zh_091", "text": "游泳", "category": "Actions", "difficulty": "easy" },
    { "id": "zh_092", "text": "打太极", "category": "Actions", "difficulty": "easy" },
    { "id": "zh_093", "text": "下棋", "category": "Actions", "difficulty": "easy" },
    { "id": "zh_094", "text": "打麻将", "category": "Actions", "difficulty": "easy" },
    { "id": "zh_095", "text": "骑自行车", "category": "Actions", "difficulty": "easy" },
    { "id": "zh_096", "text": "放风筝", "category": "Actions", "difficulty": "medium" },
    { "id": "zh_097", "text": "舞龙", "category": "Actions", "difficulty": "medium" },
    { "id": "zh_098", "text": "舞狮", "category": "Actions", "difficulty": "medium" },
    { "id": "zh_099", "text": "打功夫", "category": "Actions", "difficulty": "medium" },
    { "id": "zh_100", "text": "包饺子", "category": "Actions", "difficulty": "easy" },
    { "id": "zh_101", "text": "算命", "category": "Actions", "difficulty": "hard" },
    { "id": "zh_102", "text": "刺绣", "category": "Actions", "difficulty": "hard" },
    { "id": "zh_103", "text": "吹糖人", "category": "Actions", "difficulty": "hard" },
    { "id": "zh_104", "text": "捏泥人", "category": "Actions", "difficulty": "medium" },
    { "id": "zh_105", "text": "踢毽子", "category": "Actions", "difficulty": "medium" },
    { "id": "zh_106", "text": "写毛笔字", "category": "Actions", "difficulty": "medium" },
    { "id": "zh_107", "text": "剪纸", "category": "Actions", "difficulty": "medium" },
    { "id": "zh_108", "text": "拔河", "category": "Actions", "difficulty": "easy" },
    { "id": "zh_109", "text": "摔跤", "category": "Actions", "difficulty": "easy" },
    { "id": "zh_110", "text": "爬山", "category": "Actions", "difficulty": "easy" },
    { "id": "zh_111", "text": "打水漂", "category": "Actions", "difficulty": "easy" },
    { "id": "zh_112", "text": "扭秧歌", "category": "Actions", "difficulty": "hard" },
    { "id": "zh_113", "text": "敲锣打鼓", "category": "Actions", "difficulty": "medium" },
    { "id": "zh_114", "text": "拨算盘", "category": "Actions", "difficulty": "hard" },
    { "id": "zh_115", "text": "唱京剧", "category": "Actions", "difficulty": "hard" },
    { "id": "zh_116", "text": "钓鱼", "category": "Actions", "difficulty": "easy" },
    { "id": "zh_117", "text": "采茶", "category": "Actions", "difficulty": "medium" },
    { "id": "zh_118", "text": "打陀螺", "category": "Actions", "difficulty": "medium" },
    { "id": "zh_119", "text": "划船", "category": "Actions", "difficulty": "easy" },
    { "id": "zh_120", "text": "放鞭炮", "category": "Actions", "difficulty": "easy" },

    { "id": "zh_121", "text": "算盘", "category": "Objects", "difficulty": "easy" },
    { "id": "zh_122", "text": "灯笼", "category": "Objects", "difficulty": "easy" },
    { "id": "zh_123", "text": "折扇", "category": "Objects", "difficulty": "easy" },
    { "id": "zh_124", "text": "筷子", "category": "Objects", "difficulty": "easy" },
    { "id": "zh_125", "text": "风筝", "category": "Objects", "difficulty": "easy" },
    { "id": "zh_126", "text": "茶壶", "category": "Objects", "difficulty": "easy" },
    { "id": "zh_127", "text": "毛笔", "category": "Objects", "difficulty": "medium" },
    { "id": "zh_128", "text": "二胡", "category": "Objects", "difficulty": "medium" },
    { "id": "zh_129", "text": "琵琶", "category": "Objects", "difficulty": "medium" },
    { "id": "zh_130", "text": "如意", "category": "Objects", "difficulty": "hard" },
    { "id": "zh_131", "text": "铜锣", "category": "Objects", "difficulty": "medium" },
    { "id": "zh_132", "text": "鞭炮", "category": "Objects", "difficulty": "easy" },
    { "id": "zh_133", "text": "红包", "category": "Objects", "difficulty": "easy" },
    { "id": "zh_134", "text": "印章", "category": "Objects", "difficulty": "medium" },
    { "id": "zh_135", "text": "围棋", "category": "Objects", "difficulty": "hard" },
    { "id": "zh_136", "text": "象棋", "category": "Objects", "difficulty": "easy" },
    { "id": "zh_137", "text": "葫芦", "category": "Objects", "difficulty": "easy" },
    { "id": "zh_138", "text": "古筝", "category": "Objects", "difficulty": "medium" },
    { "id": "zh_139", "text": "唢呐", "category": "Objects", "difficulty": "hard" },
    { "id": "zh_140", "text": "盔甲", "category": "Objects", "difficulty": "easy" },
    { "id": "zh_141", "text": "砚台", "category": "Objects", "difficulty": "hard" },
    { "id": "zh_142", "text": "拨浪鼓", "category": "Objects", "difficulty": "medium" },
    { "id": "zh_143", "text": "风水罗盘", "category": "Objects", "difficulty": "hard" },
    { "id": "zh_144", "text": "铁锅", "category": "Objects", "difficulty": "easy" },
    { "id": "zh_145", "text": "蒸笼", "category": "Objects", "difficulty": "easy" },
    { "id": "zh_146", "text": "竹简", "category": "Objects", "difficulty": "hard" },
    { "id": "zh_147", "text": "珠帘", "category": "Objects", "difficulty": "medium" },
    { "id": "zh_148", "text": "铁扇", "category": "Objects", "difficulty": "medium" },
    { "id": "zh_149", "text": "竹篮", "category": "Objects", "difficulty": "easy" },
    { "id": "zh_150", "text": "玉佩", "category": "Objects", "difficulty": "medium" },

    { "id": "zh_151", "text": "皇帝", "category": "People", "difficulty": "easy" },
    { "id": "zh_152", "text": "功夫大师", "category": "People", "difficulty": "easy" },
    { "id": "zh_153", "text": "渔夫", "category": "People", "difficulty": "easy" },
    { "id": "zh_154", "text": "茶农", "category": "People", "difficulty": "easy" },
    { "id": "zh_155", "text": "书法家", "category": "People", "difficulty": "medium" },
    { "id": "zh_156", "text": "太监", "category": "People", "difficulty": "medium" },
    { "id": "zh_157", "text": "京剧演员", "category": "People", "difficulty": "medium" },
    { "id": "zh_158", "text": "道士", "category": "People", "difficulty": "medium" },
    { "id": "zh_159", "text": "风水师", "category": "People", "difficulty": "hard" },
    { "id": "zh_160", "text": "说书人", "category": "People", "difficulty": "hard" },
    { "id": "zh_161", "text": "杂技演员", "category": "People", "difficulty": "easy" },
    { "id": "zh_162", "text": "算命先生", "category": "People", "difficulty": "medium" },
    { "id": "zh_163", "text": "铁匠", "category": "People", "difficulty": "medium" },
    { "id": "zh_164", "text": "牧羊人", "category": "People", "difficulty": "easy" },
    { "id": "zh_165", "text": "制茶师", "category": "People", "difficulty": "hard" },
    { "id": "zh_166", "text": "皇后", "category": "People", "difficulty": "easy" },
    { "id": "zh_167", "text": "刺客", "category": "People", "difficulty": "medium" },
    { "id": "zh_168", "text": "侠客", "category": "People", "difficulty": "medium" },
    { "id": "zh_169", "text": "郎中", "category": "People", "difficulty": "hard" },
    { "id": "zh_170", "text": "状元", "category": "People", "difficulty": "hard" },
    { "id": "zh_171", "text": "镖师", "category": "People", "difficulty": "hard" },
    { "id": "zh_172", "text": "渔翁", "category": "People", "difficulty": "easy" },
    { "id": "zh_173", "text": "农夫", "category": "People", "difficulty": "easy" },
    { "id": "zh_174", "text": "樵夫", "category": "People", "difficulty": "medium" },
    { "id": "zh_175", "text": "木匠", "category": "People", "difficulty": "easy" },
    { "id": "zh_176", "text": "厨师", "category": "People", "difficulty": "easy" },
    { "id": "zh_177", "text": "和尚", "category": "People", "difficulty": "easy" },
    { "id": "zh_178", "text": "媒婆", "category": "People", "difficulty": "hard" },
    { "id": "zh_179", "text": "戏班班主", "category": "People", "difficulty": "hard" },
    { "id": "zh_180", "text": "船夫", "category": "People", "difficulty": "easy" },

    { "id": "zh_181", "text": "彩虹", "category": "Nature", "difficulty": "easy" },
    { "id": "zh_182", "text": "台风", "category": "Nature", "difficulty": "easy" },
    { "id": "zh_183", "text": "雪崩", "category": "Nature", "difficulty": "medium" },
    { "id": "zh_184", "text": "海啸", "category": "Nature", "difficulty": "medium" },
    { "id": "zh_185", "text": "萤火虫", "category": "Nature", "difficulty": "easy" },
    { "id": "zh_186", "text": "极光", "category": "Nature", "difficulty": "medium" },
    { "id": "zh_187", "text": "流沙", "category": "Nature", "difficulty": "easy" },
    { "id": "zh_188", "text": "钟乳石", "category": "Nature", "difficulty": "hard" },
    { "id": "zh_189", "text": "珊瑚礁", "category": "Nature", "difficulty": "easy" },
    { "id": "zh_190", "text": "干旱", "category": "Nature", "difficulty": "medium" },
    { "id": "zh_191", "text": "沙尘暴", "category": "Nature", "difficulty": "medium" },
    { "id": "zh_192", "text": "雷暴", "category": "Nature", "difficulty": "easy" },
    { "id": "zh_193", "text": "蜃景", "category": "Nature", "difficulty": "hard" },
    { "id": "zh_194", "text": "间歇泉", "category": "Nature", "difficulty": "hard" },
    { "id": "zh_195", "text": "冰雹", "category": "Nature", "difficulty": "medium" },
    { "id": "zh_196", "text": "日食", "category": "Nature", "difficulty": "medium" },
    { "id": "zh_197", "text": "暴风雪", "category": "Nature", "difficulty": "easy" },
    { "id": "zh_198", "text": "地震", "category": "Nature", "difficulty": "easy" },
    { "id": "zh_199", "text": "漩涡", "category": "Nature", "difficulty": "medium" },
    { "id": "zh_200", "text": "流星雨", "category": "Nature", "difficulty": "medium" },
    { "id": "zh_201", "text": "天坑", "category": "Nature", "difficulty": "hard" },
    { "id": "zh_202", "text": "龙卷风", "category": "Nature", "difficulty": "easy" },
    { "id": "zh_203", "text": "浓雾", "category": "Nature", "difficulty": "easy" },
    { "id": "zh_204", "text": "潮池", "category": "Nature", "difficulty": "hard" },
    { "id": "zh_205", "text": "泥石流", "category": "Nature", "difficulty": "medium" },
    { "id": "zh_206", "text": "山火", "category": "Nature", "difficulty": "easy" },
    { "id": "zh_207", "text": "梅雨", "category": "Nature", "difficulty": "medium" },
    { "id": "zh_208", "text": "涨潮", "category": "Nature", "difficulty": "medium" },
    { "id": "zh_209", "text": "尘卷风", "category": "Nature", "difficulty": "hard" },
    { "id": "zh_210", "text": "霜冻", "category": "Nature", "difficulty": "easy" }
  ]
}
